{
  "ibz_geometry": {
    "n_total": 325,
    "grid_note": "symmetry_type=none rectangle [-pi,pi] x [0,pi], 25x13",
    "group_sizes": {
      "ky0": 25,
      "kx0": 13,
      "kx0_only": 12,
      "corners": 4,
      "edge": 72,
      "interior": 253
    },
    "ky0_fraction": 0.07692307692307693,
    "kx0_fraction": 0.04,
    "ky0_is_ibz_bottom_edge": true,
    "kx0_is_mostly_interior_line": true,
    "gamma_x_waves": [
      0,
      1,
      2,
      3,
      4,
      5,
      6,
      7,
      8,
      9,
      10,
      11,
      12,
      13,
      14,
      15,
      16,
      17,
      18,
      19,
      20,
      21,
      22,
      23,
      24
    ],
    "design_symmetry": "p4mm",
    "wavevector_symmetry": "none (half-plane ky>=0)"
  },
  "training_exposure": {
    "n_train_folds": 48,
    "n_pick_per_geom_band": 65,
    "pick_probability": 0.2,
    "total_wave_counts": {
      "19": 57622,
      "31": 57441,
      "33": 57642,
      "35": 57653,
      "38": 57452,
      "50": 57604,
      "52": 57902,
      "55": 57157,
      "58": 57945,
      "59": 57564,
      "60": 57206,
      "63": 57554,
      "69": 57886,
      "72": 57774,
      "74": 57396,
      "84": 57582,
      "85": 57303,
      "86": 57088,
      "91": 57673,
      "120": 57582,
      "122": 57383,
      "123": 57845,
      "124": 57771,
      "125": 57507,
      "129": 57639,
      "135": 58004,
      "141": 58154,
      "142": 57625,
      "148": 57515,
      "149": 58157,
      "155": 57946,
      "161": 57466,
      "163": 57203,
      "169": 57651,
      "180": 57497,
      "183": 57578,
      "186": 57582,
      "187": 57418,
      "191": 58273,
      "196": 57497,
      "198": 57876,
      "200": 57512,
      "203": 57080,
      "208": 57791,
      "215": 57281,
      "219": 57694,
      "222": 57334,
      "223": 57866,
      "229": 57350,
      "231": 57634,
      "233": 57392,
      "238": 57310,
      "248": 57657,
      "254": 57684,
      "261": 57751,
      "277": 57758,
      "285": 57325,
      "294": 57191,
      "295": 57836,
      "307": 57570,
      "308": 57485,
      "313": 57545,
      "317": 57286,
      "318": 57183,
      "320": 57563,
      "6": 57619,
      "12": 57206,
      "13": 57595,
      "16": 57728,
      "22": 57641,
      "29": 57713,
      "34": 57469,
      "37": 57596,
      "39": 57531,
      "43": 57334,
      "61": 57971,
      "64": 57820,
      "65": 57490,
      "67": 57570,
      "68": 57981,
      "78": 57352,
      "83": 57788,
      "87": 57298,
      "88": 57616,
      "94": 57664,
      "97": 57545,
      "101": 57674,
      "106": 57483,
      "118": 57338,
      "119": 57849,
      "127": 57404,
      "139": 57520,
      "145": 57721,
      "150": 57687,
      "159": 57463,
      "164": 57755,
      "175": 57648,
      "182": 57451,
      "193": 57115,
      "194": 57583,
      "197": 57880,
      "201": 57627,
      "210": 57606,
      "217": 57489,
      "220": 57849,
      "245": 57161,
      "250": 57843,
      "252": 57549,
      "253": 57764,
      "263": 57665,
      "274": 57628,
      "276": 57480,
      "278": 57614,
      "284": 57753,
      "287": 57419,
      "290": 57837,
      "292": 57239,
      "40": 57684,
      "48": 57644,
      "89": 57741,
      "95": 57601,
      "98": 58056,
      "99": 57357,
      "103": 57535,
      "104": 57801,
      "105": 57374,
      "107": 57511,
      "111": 57302,
      "126": 57408,
      "128": 57630,
      "131": 57380,
      "146": 57319,
      "153": 57253,
      "154": 57867,
      "162": 57526,
      "171": 57409,
      "179": 57677,
      "192": 57345,
      "202": 57637,
      "205": 57792,
      "211": 57945,
      "213": 57492,
      "214": 57956,
      "224": 57772,
      "226": 57600,
      "255": 57219,
      "257": 57753,
      "259": 57526,
      "282": 57397,
      "291": 57779,
      "293": 57867,
      "296": 57684,
      "299": 57984,
      "300": 57411,
      "306": 57377,
      "316": 57987,
      "7": 57786,
      "11": 57845,
      "15": 57431,
      "44": 57587,
      "49": 57902,
      "57": 57453,
      "114": 57495,
      "115": 57446,
      "156": 57743,
      "157": 57510,
      "160": 57777,
      "165": 57713,
      "166": 57525,
      "178": 57748,
      "195": 57831,
      "209": 57366,
      "216": 57533,
      "227": 57431,
      "232": 57458,
      "234": 57686,
      "235": 57281,
      "239": 57581,
      "246": 57828,
      "247": 57577,
      "251": 57663,
      "258": 57336,
      "264": 57656,
      "266": 57508,
      "281": 57559,
      "304": 57633,
      "309": 57249,
      "324": 57545,
      "0": 57852,
      "3": 57439,
      "4": 58314,
      "5": 57562,
      "8": 57796,
      "10": 57545,
      "17": 57930,
      "21": 57806,
      "23": 57427,
      "25": 57422,
      "28": 57538,
      "30": 57863,
      "70": 57470,
      "71": 57754,
      "82": 57697,
      "93": 57586,
      "116": 57245,
      "121": 57961,
      "130": 57344,
      "133": 57510,
      "151": 57561,
      "167": 57423,
      "172": 57283,
      "176": 57650,
      "190": 57501,
      "206": 57156,
      "242": 57343,
      "265": 57434,
      "270": 57530,
      "273": 57912,
      "319": 57333,
      "2": 57661,
      "26": 57803,
      "36": 57460,
      "42": 57969,
      "47": 57433,
      "51": 57906,
      "96": 57494,
      "108": 57498,
      "112": 57897,
      "158": 57864,
      "185": 57712,
      "236": 57404,
      "237": 57642,
      "275": 57244,
      "286": 57774,
      "289": 57770,
      "310": 57751,
      "9": 57556,
      "18": 57839,
      "75": 57495,
      "117": 57736,
      "134": 57515,
      "136": 57487,
      "143": 57835,
      "147": 57942,
      "184": 57611,
      "189": 57619,
      "243": 57297,
      "268": 57360,
      "271": 57569,
      "272": 57516,
      "302": 57444,
      "305": 57642,
      "311": 57565,
      "24": 57774,
      "41": 57603,
      "62": 57398,
      "109": 57617,
      "132": 57483,
      "152": 57699,
      "170": 57783,
      "174": 57868,
      "240": 57144,
      "260": 57741,
      "267": 57517,
      "297": 57436,
      "301": 57833,
      "314": 57508,
      "321": 57576,
      "81": 57556,
      "92": 57969,
      "110": 57243,
      "173": 57946,
      "256": 57744,
      "32": 57773,
      "90": 57749,
      "113": 56991,
      "137": 57658,
      "168": 57298,
      "207": 57583,
      "212": 57746,
      "218": 57525,
      "279": 57837,
      "280": 57793,
      "315": 57562,
      "323": 57438,
      "46": 57467,
      "76": 57408,
      "80": 57852,
      "177": 57847,
      "181": 57847,
      "188": 57794,
      "262": 57612,
      "283": 57583,
      "298": 58145,
      "322": 57472,
      "27": 57415,
      "288": 57580,
      "138": 57798,
      "204": 57588,
      "221": 57872,
      "225": 57743,
      "244": 57675,
      "20": 57371,
      "53": 57919,
      "54": 57748,
      "79": 57594,
      "1": 57882,
      "45": 57733,
      "56": 57332,
      "77": 57730,
      "199": 57366,
      "228": 57265,
      "269": 57716,
      "140": 57639,
      "144": 57501,
      "249": 57452,
      "312": 57408,
      "241": 57203,
      "303": 57682,
      "230": 57715,
      "102": 57298,
      "14": 57829,
      "100": 57675,
      "66": 57781,
      "73": 57983
    },
    "by_group": {
      "ky0": {
        "n_waves": 25,
        "mean_count": 57682.24,
        "min_count": 57206,
        "max_count": 58314,
        "mean_frac_of_max": 0.20028555555555555
      },
      "kx0": {
        "n_waves": 13,
        "mean_count": 57524.92307692308,
        "min_count": 57206,
        "max_count": 57897,
        "mean_frac_of_max": 0.19973931623931623
      },
      "kx0_only": {
        "n_waves": 12,
        "mean_count": 57551.5,
        "min_count": 57298,
        "max_count": 57897,
        "mean_frac_of_max": 0.1998315972222222
      },
      "corners": {
        "n_waves": 4,
        "mean_count": 57645.5,
        "min_count": 57411,
        "max_count": 57852,
        "mean_frac_of_max": 0.2001579861111111
      },
      "edge": {
        "n_waves": 72,
        "mean_count": 57613.01388888889,
        "min_count": 57183,
        "max_count": 58314,
        "mean_frac_of_max": 0.20004518711419753
      },
      "interior": {
        "n_waves": 253,
        "mean_count": 57596.296442687744,
        "min_count": 56991,
        "max_count": 58273,
        "mean_frac_of_max": 0.1999871404259991
      }
    },
    "ky0_vs_interior_mean_ratio": 1.0014921715912373
  }
}